nonebot_plugin_shutup-0.1.0.dist-info/METADATA
nonebot_plugin_shutup-0.1.0.dist-info/WHEEL
nonebot_plugin_shutup-0.1.0.dist-info/entry_points.txt
nonebot_plugin_shutup-0.1.0.dist-info/licenses/LICENSE
nonebot_plugin_shutup/__init__.py
nonebot_plugin_shutup/__main__.py
nonebot_plugin_shutup/config.py
nonebot_plugin_shutup/rule.py
nonebot_plugin_shutup-0.1.0.dist-info/RECORD
