Metadata-Version: 2.1
Name: nonebot-plugin-shutup
Version: 0.1.0
Summary: 基于 NoneBot2 的 插件，用于机器人当前会话闭嘴
Keywords: nonebot2,plugin
Author-Email: Agnes_Digital <Z735803792@163.com>
License: MIT
Classifier: License :: OSI Approved :: MIT License
Classifier: Programming Language :: Python
Classifier: Programming Language :: Python :: 3
Classifier: Programming Language :: Python :: 3.9
Classifier: Programming Language :: Python :: 3.10
Classifier: Programming Language :: Python :: 3.11
Classifier: Programming Language :: Python :: 3.12
Classifier: Operating System :: OS Independent
Project-URL: homepage, https://github.com/Agnes4m/nonebot_pluigin_shutup
Requires-Python: <4.0,>=3.8
Requires-Dist: nonebot2>=2.2.0
